models_package/models/__init__.py
models_package/models/abstract_model.py
models_package/models/river_segmentation_model.py
models_package/models/water_segmentation_model.py
models_package/schemas/__init__.py
models_package/schemas/models.py
models_package-0.1.6.dist-info/METADATA
models_package-0.1.6.dist-info/WHEEL
models_package-0.1.6.dist-info/licenses/LICENSE
models_package-0.1.6.dist-info/RECORD
