Metadata-Version: 2.4
Name: models-package
Version: 0.1.6
Summary: A collection of segmentation models for water and river detection
Project-URL: Homepage, https://github.com/deepblue597/models_package
Project-URL: Repository, https://github.com/deepblue597/models_package.git
Project-URL: Issues, https://github.com/deepblue597/models_package/issues
Author-email: Jason <ikakandris@gmail.com>
License: MIT
License-File: LICENSE
Keywords: deep-learning,pytorch,river-detection,satellite-imagery,segmentation,water-detection
Classifier: Development Status :: 3 - Alpha
Classifier: Intended Audience :: Developers
Classifier: Intended Audience :: Science/Research
Classifier: License :: OSI Approved :: MIT License
Classifier: Operating System :: OS Independent
Classifier: Programming Language :: Python :: 3
Classifier: Programming Language :: Python :: 3.12
Classifier: Topic :: Scientific/Engineering :: Artificial Intelligence
Classifier: Topic :: Scientific/Engineering :: Image Processing
Classifier: Topic :: Software Development :: Libraries :: Python Modules
Requires-Python: >=3.12
Requires-Dist: albumentations>=1.0.0
Requires-Dist: db-connectors>=0.1.0
Requires-Dist: numpy>=1.21.0
Requires-Dist: opencv-python>=4.5.0
Requires-Dist: pydantic>=2.0.0
Requires-Dist: rasterio>=1.2.0
Requires-Dist: segmentation-models-pytorch>=0.3.0
Requires-Dist: tifffile>=2021.0.0
Requires-Dist: torch>=1.9.0
Requires-Dist: torchvision>=0.10.0
Provides-Extra: dev
Requires-Dist: black>=22.0; extra == 'dev'
Requires-Dist: mypy>=1.0; extra == 'dev'
Requires-Dist: pytest>=6.0; extra == 'dev'
Requires-Dist: ruff>=0.1.0; extra == 'dev'
